{
    "seed": 1234,
    "gpu": "3",
    "dataset": "mnist",
    "image_shape": [32,32,1],
    "batch_size": 64,
    "model": "flow",
    "n_bits": 8,
    "lambda_reg": 0.00005,
    "lambda_mse": -1,
    "residual_blocks": 2,
    "n_scale": 4,
    "base_dim": 32,
    "bottleneck": 1,
    "use_aff": 1,
    "use_batch_norm": 0,
    "skip": 1,
    "data_constraint": 0.9,
    "epochs": 1000,
    "lr": 0.001,
    "decay_steps": 100000,
    "decay_rate": 0.5,
    "clip_gradient": 100,
    "restore_from": "",
    "exp_dir": "./exp/mnist/rnvp",
    "print_freq": -1,
    "summ_freq": 100,
    "num_samples": 1,
    "sample_std": 1.0
}